maplewood/__init__.py
maplewood/chainsaw.py
maplewood-0.3.0.dist-info/LICENSE
maplewood-0.3.0.dist-info/METADATA
maplewood-0.3.0.dist-info/WHEEL
maplewood-0.3.0.dist-info/top_level.txt
maplewood-0.3.0.dist-info/RECORD
