Metadata-Version: 2.1
Name: maplewood
Version: 0.3.0
Summary: A package for logging in plaintext
Author: Gaurav Prajapati
Project-URL: Homepage, https://github.com/gaurav5-5/maplewood
Project-URL: Bug Tracker, https://github.com/gaurav5-5/maplewood/issues
Classifier: Programming Language :: Python :: 3
Classifier: License :: OSI Approved :: MIT License
Classifier: Operating System :: OS Independent
Requires-Python: >=3.7
License-File: LICENSE
